nirtorch/__init__.py
nirtorch/from_nir.py
nirtorch/graph.py
nirtorch/graph_executor.py
nirtorch/graph_utils.py
nirtorch/nir_interpreter.py
nirtorch/to_nir.py
nirtorch/torch_tracer.py
nirtorch/utils.py
nirtorch-2.6.dist-info/licenses/LICENSE
nirtorch-2.6.dist-info/METADATA
nirtorch-2.6.dist-info/WHEEL
nirtorch-2.6.dist-info/top_level.txt
nirtorch-2.6.dist-info/RECORD
