Metadata-Version: 2.4
Name: nirtorch
Version: 2.6
Summary: Neuromorphic Intermediate Representation
Author-email: Steven Abreu <s.abreu@rug.nl>, Felix Bauer <felix.bauer@synsen.ai>, Jason Eshraghian <jeshragh@ucsc.edu>, Matthias Jobst <matthias.jobst2@tu-dresden.de>, Gregor Lenz <mail@lenzgregor.com>, Jens Egholm Pedersen <jens@jepedersen.dk>, Sadique Sheik <sadique.sheik@synsense.ai>
Keywords: neuromorphic,intermediate,representation
Classifier: Development Status :: 4 - Beta
Classifier: Intended Audience :: Developers
Classifier: Intended Audience :: Science/Research
Classifier: License :: OSI Approved :: BSD License
Classifier: Programming Language :: Python :: 3
Classifier: Topic :: Scientific/Engineering :: Artificial Intelligence
Classifier: Topic :: Scientific/Engineering :: Information Analysis
Classifier: Topic :: Scientific/Engineering :: Mathematics
Classifier: Topic :: Scientific/Engineering :: Physics
Classifier: Topic :: Software Development :: Libraries :: Python Modules
License-File: LICENSE
Requires-Dist: torch
Requires-Dist: nir>=1.0.6
Dynamic: license-file
